nanocli/__init__.py
nanocli/config.py
nanocli/core.py
nanocli-0.1.1.dist-info/METADATA
nanocli-0.1.1.dist-info/WHEEL
nanocli-0.1.1.dist-info/licenses/LICENSE
nanocli-0.1.1.dist-info/RECORD
