Metadata-Version: 2.4
Name: nanocli
Version: 0.1.1
Summary: Recursive hierarchical CLI framework with typed configs and YAML synthesis
Project-URL: Homepage, https://github.com/example/nanocli
Project-URL: Repository, https://github.com/example/nanocli
Author-email: Author <author@example.com>
License-Expression: MIT
License-File: LICENSE
Keywords: cli,config,typer,yaml
Classifier: Development Status :: 3 - Alpha
Classifier: Environment :: Console
Classifier: Intended Audience :: Developers
Classifier: License :: OSI Approved :: MIT License
Classifier: Programming Language :: Python :: 3
Classifier: Programming Language :: Python :: 3.10
Classifier: Programming Language :: Python :: 3.11
Classifier: Programming Language :: Python :: 3.12
Classifier: Typing :: Typed
Requires-Python: >=3.10
Requires-Dist: omegaconf>=2.3.0
Requires-Dist: rich>=13.0.0
Provides-Extra: dev
Requires-Dist: mkdocs-material>=9.5.0; extra == 'dev'
Requires-Dist: mkdocstrings[python]>=0.24.0; extra == 'dev'
Requires-Dist: mypy>=1.8.0; extra == 'dev'
Requires-Dist: pre-commit>=3.6.0; extra == 'dev'
Requires-Dist: pytest-cov>=4.1.0; extra == 'dev'
Requires-Dist: pytest-xdist>=3.5.0; extra == 'dev'
Requires-Dist: pytest>=9.0.0; extra == 'dev'
Requires-Dist: ruff>=0.14.8; extra == 'dev'
